langswarm/backend/__init__.py
langswarm/backend/main.py
langswarm/backend/app/__init__.py
langswarm/backend/app/api.py
langswarm/tests/__init__.py
langswarm_backend-0.0.6.dist-info/LICENSE
langswarm_backend-0.0.6.dist-info/METADATA
langswarm_backend-0.0.6.dist-info/WHEEL
langswarm_backend-0.0.6.dist-info/top_level.txt
langswarm_backend-0.0.6.dist-info/RECORD
