Metadata-Version: 2.2
Name: langswarm-backend
Version: 0.0.6
Summary: A FastAPI-based backend enabling seamless multi-agent orchestration and API integration for LangSwarm applications.
Home-page: https://github.com/aekdahl/langswarm-backend
Author: Alexander Ekdahl
Author-email: alexander.ekdahl@gmail.com
License: MIT
Classifier: Development Status :: 3 - Alpha
Classifier: Intended Audience :: Developers
Classifier: License :: OSI Approved :: MIT License
Classifier: Programming Language :: Python :: 3.8
Classifier: Programming Language :: Python :: 3.9
Classifier: Programming Language :: Python :: 3.10
Classifier: Programming Language :: Python :: 3.11
Requires-Python: >=3.8
License-File: LICENSE
Requires-Dist: fastapi==0.100.0
Requires-Dist: uvicorn[standard]==0.23.1
Provides-Extra: dev
Requires-Dist: pytest; extra == "dev"
Requires-Dist: black; extra == "dev"
Requires-Dist: flake8; extra == "dev"
Dynamic: author
Dynamic: author-email
Dynamic: classifier
Dynamic: description
Dynamic: description-content-type
Dynamic: home-page
Dynamic: license
Dynamic: provides-extra
Dynamic: requires-dist
Dynamic: requires-python
Dynamic: summary
